{
"char": "同",
"level": "1",
"info": {
"gloss": "same, similar; together with",
"pron": "tóng, tòng"
},
"words": [
[
"同学",
1,
"tóng xué",
"to study at the same school; fellow student; classmate; CL:位[wèi],个[gè]"
],
[
"不同",
2,
"bù tóng",
"different; distinct; not the same; not alike"
],
[
"同时",
2,
"tóng shí",
"at the same time; simultaneously"
],
[
"同事",
2,
"tóng shì",
"colleague; co-worker; CL:个[gè],位[wèi]"
],
[
"同样",
2,
"tóng yàng",
"same; equal; equivalent"
],
[
"相同",
2,
"xiāng tóng",
"identical; same"
],
[
"共同",
3,
"gòng tóng",
"common; joint; jointly; together; collaborative"
],
[
"同意",
3,
"tóng yì",
"to agree; to consent; to approve"
],
[
"合同",
4,
"hé tong",
"(business) contract; CL:个[gè]"
],
[
"同情",
4,
"tóng qíng",
"to sympathize with; sympathy"
],
[
"胡同儿",
5,
"hú tòng",
"lane; alley; CL:条[tiáo]"
],
[
"如同",
5,
"rú tóng",
"like; as"
],
[
"陪同",
6,
"péi tóng",
"to accompany"
],
[
"认同",
6,
"rèn tóng",
"to approve of; to endorse; to acknowledge; to recognize; to identify oneself with"
],
[
"同",
6,
"tóng",
"(used in given names); variant of 同[tóng]"
],
[
"同",
6,
"tóng",
"like; same; similar; together; alike; with"
],
[
"同",
6,
"tòng",
"see 胡同[hú tòng]"
],
[
"同胞",
6,
"tóng bāo",
"born of the same parents; sibling; fellow citizen; compatriot"
],
[
"同行",
6,
"tóng háng",
"person of the same profession; of the same trade, occupation or industry"
],
[
"同行",
6,
"tóng xíng",
"to journey together"
],
[
"同期",
6,
"tóng qī",
"the corresponding time period (in a different year etc); concurrent; synchronous"
],
[
"同一",
6,
"tóng yī",
"identical; the same"
],
[
"一同",
6,
"yī tóng",
"along; together"
],
[
"不同寻常",
7,
"bù tóng xún cháng",
"out of the ordinary; unusual"
],
[
"不约而同",
7,
"bù yuē ér tóng",
"to agree by chance (idiom); taking the same action without prior consultation"
],
[
"大同小异",
7,
"dà tóng xiǎo yì",
"virtually the same; differing only on small points"
],
[
"共同体",
7,
"gòng tóng tǐ",
"community"
],
[
"截然不同",
7,
"jié rán bù tóng",
"entirely different; different as black and white"
],
[
"雷同",
7,
"léi tóng",
"mirroring others; identical"
],
[
"同伴",
7,
"tóng bàn",
"companion; comrade; fellow"
],
[
"同步",
7,
"tóng bù",
"synchronous; to synchronize; to keep step with"
],
[
"同等",
7,
"tóng děng",
"equal to; having the same social class or status"
],
[
"同感",
7,
"tóng gǎn",
"(have the) same feeling; similar impression; common feeling"
],
[
"同伙",
7,
"tóng huǒ",
"colleague; co-conspirator; accomplice"
],
[
"同类",
7,
"tóng lèi",
"similar; same type; alike"
],
[
"同盟",
7,
"tóng méng",
"alliance"
],
[
"同年",
7,
"tóng nián",
"the same year"
],
[
"同人",
7,
"tóng rén",
"people from the same workplace or profession; co-worker; colleague; pop culture enthusiasts who create fan fiction etc"
],
[
"同志",
7,
"tóng zhì",
"comrade; (slang) homosexual; CL:个[gè]"
],
[
"同舟共济",
7,
"tóng zhōu gòng jì",
"cross a river in the same boat (idiom); fig. having common interests; obliged to collaborate towards common goals"
],
[
"协同",
7,
"xié tóng",
"to cooperate; in coordination with; coordinated; collaborate; collaboration; collaborative"
],
[
"异口同声",
7,
"yì kǒu tóng shēng",
"different mouths, same voice; to speak in unison (idiom)"
],
[
"有所不同",
7,
"yǒu suǒ bù tóng",
"to differ to some extent (idiom)"
],
[
"与此同时",
7,
"yǔ cǐ tóng shí",
"at the same time; meanwhile"
],
[
"与众不同",
7,
"yǔ zhòng bù tóng",
"to stand out from the masses (idiom)"
],
[
"赞同",
7,
"zàn tóng",
"to approve of; to endorse; (vote) in favor"
],
[
"赞同",
7,
"zàn tóng",
"to approve of; to endorse; (vote) in favor"
]
],
"extraWords": [
[
"同性恋",
98.31,
"tóng xìng liàn",
"homosexuality; gay person; gay love"
],
[
"同学们",
20.88,
"???",
"???"
],
[
"同一个",
14.79,
"???",
"???"
],
[
"同志们",
13.86,
"???",
"???"
],
[
"共同点",
11.48,
"gòng tóng diǎn",
"common ground"
],
[
"会同",
8.91,
"Huì tóng",
"Huitong county in Huaihua 怀化[Huái huà], Hunan"
],
[
"会同",
8.91,
"huì tóng",
"to handle sth jointly"
],
[
"同情心",
7.81,
"???",
"???"
],
[
"同居",
6.28,
"tóng jū",
"to live together"
],
[
"等同",
5.9,
"děng tóng",
"to equate; equal to"
],
[
"连同",
5.68,
"lián tóng",
"together with; along with"
],
[
"大同",
5.41,
"Dà tóng",
"(Confucianism) Great Harmony (concept of an ideal society)"
],
[
"同业",
5.4,
"tóng yè",
"same trade or business; person in the same trade or business"
],
[
"同谋",
5.34,
"tóng móu",
"to conspire with sb; to plot; a conspirator; a partner in crime; an accomplice"
]
],
"strokes": [
"M 282 732 Q 258 751 232 761 Q 222 762 214 754 Q 210 747 218 735 Q 276 576 226 266 Q 216 215 198 162 Q 188 134 193 111 Q 202 72 215 58 Q 227 42 239 57 Q 267 90 279 237 Q 273 249 289 563 Q 293 650 299 687 C 303 717 303 717 282 732 Z",
"M 299 687 Q 306 687 314 689 Q 477 729 676 757 Q 703 763 716 747 Q 732 740 739 667 Q 761 424 753 148 Q 753 108 738 96 Q 720 83 631 99 Q 612 102 615 91 Q 616 82 631 77 Q 712 28 754 -11 Q 779 -33 794 -29 Q 807 -25 819 8 Q 835 60 831 135 Q 804 514 803 654 Q 802 699 815 726 Q 828 751 816 764 Q 804 780 749 807 Q 727 817 705 812 Q 543 758 282 732 C 252 729 270 681 299 687 Z",
"M 384 586 Q 351 580 375 565 Q 414 544 464 555 Q 530 568 599 583 Q 630 590 635 594 Q 642 601 639 609 Q 632 619 606 627 Q 578 631 551 621 Q 515 609 477 600 Q 434 590 384 586 Z",
"M 406 441 Q 396 447 366 453 Q 354 456 351 451 Q 344 445 352 430 Q 377 376 391 288 Q 394 261 409 243 Q 425 222 431 237 Q 435 250 434 271 L 430 302 Q 418 384 417 412 C 416 436 416 436 406 441 Z",
"M 600 324 Q 618 393 649 419 Q 664 435 651 451 Q 579 503 542 479 Q 478 458 406 441 C 377 434 388 403 417 412 Q 423 416 542 439 Q 557 443 563 437 Q 572 428 570 410 Q 563 367 554 328 C 547 299 592 295 600 324 Z",
"M 434 271 Q 440 271 448 272 Q 500 284 612 292 Q 622 293 624 301 Q 624 308 600 324 C 586 333 584 333 554 328 Q 553 328 552 328 Q 485 312 430 302 C 400 297 404 270 434 271 Z"
]
}