{
"char": "性",
"level": "3",
"info": {
"gloss": "nature, character, sex",
"pron": "xìng"
},
"words": [
[
"个性",
3,
"gè xìng",
"individuality; personality"
],
[
"性",
3,
"xìng",
"nature; character; property; quality; attribute; sexuality; sex; gender; suffix forming adjective from verb; suffix forming noun from adjective, corresponding to -ness or -ity; essence; CL:个[gè]"
],
[
"性别",
3,
"xìng bié",
"gender; sex"
],
[
"性格",
3,
"xìng gé",
"nature; disposition; temperament; character; CL:个[gè]"
],
[
"性质",
4,
"xìng zhì",
"nature; characteristic; CL:个[gè]"
],
[
"男性",
5,
"nán xìng",
"the male sex; a male"
],
[
"女性",
5,
"nǚ xìng",
"woman; the female sex"
],
[
"特性",
5,
"tè xìng",
"property; characteristic"
],
[
"性能",
5,
"xìng néng",
"function; performance"
],
[
"一次性",
6,
"yī cì xìng",
"one-off (offer); one-time; single-use; disposable (goods)"
],
[
"本性",
7,
"běn xìng",
"natural instincts; nature; inherent quality"
],
[
"恶性",
7,
"è xìng",
"malignant; wicked; vicious (circle); producing evil; rapid (decline); runaway (inflation)"
],
[
"感性",
7,
"gǎn xìng",
"perception; perceptual; sensibility; sensitive; emotional; sentimental"
],
[
"公益性",
7,
"???",
"???"
],
[
"共性",
7,
"gòng xìng",
"overall character"
],
[
"惯性",
7,
"guàn xìng",
"(physics) inertia; (fig.) force of habit; tendency to do things in the accustomed way; habitual"
],
[
"急性",
7,
"jí xìng",
"acute"
],
[
"理性",
7,
"lǐ xìng",
"reason; rationality; rational"
],
[
"良性",
7,
"liáng xìng",
"positive (in its effect); leading to good consequences; virtuous; (medicine) benign (tumor etc)"
],
[
"慢性",
7,
"màn xìng",
"slow and patient; chronic (disease); slow to take effect (e.g. a slow poison)"
],
[
"耐性",
7,
"nài xìng",
"patience; endurance"
],
[
"人性",
7,
"rén xìng",
"human nature; humanity; human; the totality of human attributes"
],
[
"韧性",
7,
"rèn xìng",
"toughness"
],
[
"属性",
7,
"shǔ xìng",
"attribute; property"
],
[
"索性",
7,
"suǒ xìng",
"you might as well (do it); simply; just"
],
[
"弹性",
7,
"tán xìng",
"flexibility; elasticity"
],
[
"天性",
7,
"tiān xìng",
"nature; innate tendency"
],
[
"性价比",
7,
"xìng jià bǐ",
"cost-performance ratio"
],
[
"性命",
7,
"xìng mìng",
"life"
],
[
"性情",
7,
"xìng qíng",
"nature; temperament"
],
[
"阳性",
7,
"yáng xìng",
"positive; masculine"
],
[
"异性",
7,
"yì xìng",
"the opposite sex; of the opposite sex; heterosexual; different in nature"
],
[
"阴性",
7,
"yīn xìng",
"negative; feminine"
],
[
"隐性",
7,
"yǐn xìng",
"hidden; crypto-; recessive (gene)"
],
[
"中性",
7,
"zhōng xìng",
"neutral"
]
],
"extraWords": [
[
"同性恋",
98.31,
"tóng xìng liàn",
"homosexuality; gay person; gay love"
],
[
"性感",
88.62,
"xìng gǎn",
"sex appeal; eroticism; sexuality; sexy"
],
[
"可能性",
38.11,
"kě néng xìng",
"possibility; probability"
],
[
"积极性",
29.86,
"jī jí xìng",
"zeal; initiative; enthusiasm; activity"
],
[
"活性",
28.17,
"huó xìng",
"(chemistry) activity; active; activated"
],
[
"重要性",
20.48,
"zhòng yào xìng",
"importance"
],
[
"性爱",
19.23,
"xìng ài",
"sex; lovemaking"
],
[
"先进性",
17.37,
"???",
"???"
],
[
"流动性",
17.3,
"liú dòng xìng",
"flowing; shifting; fluidity; mobility; liquidity (of funds)"
],
[
"稳定性",
15.93,
"wěn dìng xìng",
"stability"
],
[
"显著性",
14.58,
"???",
"???"
],
[
"针对性",
14.53,
"zhēn duì xìng",
"focus; direction; purpose; relevance"
],
[
"创造性",
13.9,
"chuàng zào xìng",
"creativeness; creativity"
],
[
"安全性",
13.77,
"ān quán xìng",
"security; safety"
],
[
"实质性",
11.89,
"shí zhì xìng",
"substantive; substantial; material; considerable"
],
[
"个性化",
10.8,
"gè xìng huà",
"to personalize; to customize; customization"
],
[
"综合性",
10.78,
"zōng hé xìng",
"synthesis"
],
[
"代表性",
10.17,
"dài biǎo xìng",
"representativeness; representative; typical"
],
[
"性骚扰",
9.72,
"xìng sāo rǎo",
"sexual harassment"
],
[
"毒性",
9.7,
"dú xìng",
"toxicity"
],
[
"任性",
9.68,
"rèn xìng",
"willful; headstrong; unruly"
],
[
"人性化",
9.6,
"rén xìng huà",
"(of a system or product etc) adapted to human needs; people-oriented; user-friendly"
],
[
"历史性",
9.06,
"lì shǐ xìng",
"historic"
],
[
"性生活",
8.76,
"xìng shēng huó",
"sex life"
],
[
"特异性",
8.4,
"tè yì xìng",
"specific; specificity; idiosyncrasy"
],
[
"可靠性",
7.87,
"kě kào xìng",
"reliability"
],
[
"全国性",
7.8,
"quán guó xìng",
"national"
],
[
"阶段性",
7.68,
"jiē duàn xìng",
"specific to a particular stage (of a project etc); interim (policy etc); occurring in stages; phased"
],
[
"性关系",
7.66,
"xìng guān xi",
"sexual relations; sexual contact; intercourse"
],
[
"定性",
7.4,
"dìng xìng",
"to determine the nature (usually of error or crime); to determine chemical composition; qualitative; fixed"
],
[
"真实性",
7.23,
"zhēn shí xìng",
"authenticity; truthfulness; veracity; reality; validity"
],
[
"变性",
7.12,
"biàn xìng",
"to denature; denaturation; to have a sex change; transsexual"
],
[
"政策性",
6.86,
"???",
"???"
],
[
"恶性肿瘤",
6.85,
"è xìng zhǒng liú",
"malignant tumor"
],
[
"性交",
6.8,
"xìng jiāo",
"sexual intercourse"
],
[
"性行为",
6.68,
"xìng xíng wéi",
"sexual behavior"
],
[
"多样性",
6.64,
"duō yàng xìng",
"variegation; diversity"
],
[
"结构性",
6.52,
"jié gòu xìng",
"structural; structured"
],
[
"敏感性",
6.51,
"mǐn gǎn xìng",
"sensitive; sensitivity"
],
[
"不确定性",
6.5,
"???",
"???"
],
[
"战略性",
6.45,
"zhàn lüè xìng",
"strategic"
],
[
"强制性",
6.43,
"???",
"???"
],
[
"血性",
6.33,
"xuè xìng",
"brave; staunch; unyielding"
],
[
"决定性",
6.32,
"jué dìng xìng",
"decisive; conclusive"
],
[
"选择性",
6.31,
"xuǎn zé xìng",
"selective; selectiveness; selectivity"
],
[
"放射性",
6.22,
"fàng shè xìng",
"radioactive"
],
[
"可行性",
6.16,
"kě xíng xìng",
"feasibility"
],
[
"先天性",
5.86,
"xiān tiān xìng",
"congenital; intrinsic; innateness"
],
[
"相关性",
5.84,
"xiāng guān xìng",
"correlation"
],
[
"线性",
5.74,
"xiàn xìng",
"linear; linearity"
],
[
"准确性",
5.7,
"zhǔn què xìng",
"accuracy"
],
[
"标志性",
5.62,
"biāo zhì xìng",
"iconic"
],
[
"性状",
5.58,
"xìng zhuàng",
"nature (i.e. properties of sth); character"
],
[
"误导性",
5.56,
"???",
"???"
],
[
"经营性",
5.54,
"???",
"???"
],
[
"灵活性",
5.51,
"líng huó xìng",
"flexibility"
],
[
"区域性",
5.48,
"qū yù xìng",
"regional"
],
[
"性欲",
5.46,
"xìng yù",
"sexual desire; lust"
],
[
"有效性",
5.43,
"yǒu xiào xìng",
"validity"
],
[
"经常性",
5.43,
"???",
"???"
],
[
"危险性",
5.34,
"???",
"???"
],
[
"合理性",
5.29,
"hé lǐ xìng",
"reason; rationality; rationale; reasonableness"
],
[
"技术性",
5.27,
"jì shù xìng",
"technical; technological"
],
[
"持续性",
5.26,
"???",
"???"
],
[
"戏剧性",
5.25,
"xì jù xìng",
"dramatic"
],
[
"独立性",
5.24,
"???",
"???"
],
[
"特殊性",
5.23,
"???",
"???"
],
[
"适应性",
5.2,
"shì yìng xìng",
"adaptability; flexibility"
],
[
"高性能",
5.16,
"gāo xìng néng",
"high performance"
],
[
"性病",
5.06,
"xìng bìng",
"sexually transmitted disease; venereal disease"
],
[
"必要性",
5.06,
"bì yào xìng",
"necessity"
],
[
"根本性",
5.03,
"???",
"???"
],
[
"群众性",
5.0,
"qún zhòng xìng",
"to do with the masses; mass (meeting, movement etc)"
]
],
"strokes": [
"M 123 507 Q 104 431 72 361 Q 57 319 79 292 Q 89 274 109 290 Q 130 309 140 345 Q 159 403 157 451 Q 158 485 147 511 Q 141 518 135 519 Q 126 516 123 507 Z",
"M 294 563 Q 330 542 368 513 Q 383 503 396 506 Q 406 507 409 520 Q 412 535 400 560 Q 390 584 299 597 Q 296 598 295 597 C 265 598 268 578 294 563 Z",
"M 295 597 Q 298 675 314 730 Q 323 745 319 758 Q 313 768 258 801 Q 236 817 215 802 Q 211 798 217 782 Q 250 733 251 654 Q 251 219 234 125 Q 228 101 222 76 Q 212 40 236 -22 Q 243 -40 251 -43 Q 257 -50 264 -41 Q 271 -37 281 -17 Q 291 8 290 38 Q 289 90 294 563 L 295 597 Z",
"M 505 502 Q 520 536 559 605 Q 568 618 552 632 Q 506 660 482 655 Q 472 651 475 637 Q 497 553 411 432 Q 399 420 376 384 Q 369 368 384 374 Q 429 386 491 480 L 505 502 Z",
"M 676 487 Q 832 526 839 531 Q 849 540 843 548 Q 836 560 806 567 Q 775 571 744 559 Q 711 549 678 537 L 627 523 Q 570 510 505 502 C 475 498 464 493 491 480 Q 492 480 495 478 Q 540 454 597 471 Q 610 475 626 476 L 676 487 Z",
"M 672 272 Q 715 282 762 290 Q 798 297 803 303 Q 812 310 807 320 Q 800 332 770 339 Q 740 346 673 322 L 624 308 Q 575 299 522 294 Q 485 287 511 270 Q 551 249 623 262 L 672 272 Z",
"M 669 114 Q 670 196 672 272 L 673 322 Q 674 407 676 487 L 678 537 Q 684 714 696 748 Q 708 767 694 781 Q 657 809 629 818 Q 613 821 599 809 Q 593 802 600 790 Q 633 736 629 677 Q 628 602 627 523 L 626 476 Q 625 394 624 308 L 623 262 Q 623 187 623 108 C 623 78 669 84 669 114 Z",
"M 623 108 Q 511 95 378 76 Q 354 75 372 55 Q 406 24 460 36 Q 605 75 928 74 Q 950 74 955 84 Q 962 97 943 112 Q 880 160 815 140 Q 755 130 669 114 L 623 108 Z"
]
}