{
"char": "日",
"level": 2,
"info": {
"gloss": "sun; day; daytime",
"pron": "rì"
},
"words": [
[
"日",
2,
"Rì",
"abbr. for 日本[Ri4 ben3], Japan"
],
[
"日",
2,
"rì",
"sun; day; date, day of the month"
],
[
"生日",
2,
"shēng rì",
"birthday; CL:個|个[ge4]"
],
[
"节日",
3,
"jié rì",
"holiday; festival; CL:個|个[ge4]"
],
[
"日记",
4,
"rì jì",
"diary; CL:則|则[ze2],本[ben3],篇[pian1]"
],
[
"日子",
5,
"rì zi",
"day; a (calendar) date; days of one's life"
],
[
"日期",
5,
"rì qī",
"date; CL:個|个[ge4]"
],
[
"日常",
5,
"rì cháng",
"daily; everyday"
],
[
"日程",
5,
"rì chéng",
"schedule; itinerary; CL:個|个[ge4]"
],
[
"日历",
5,
"rì lì",
"calendar; CL:張|张[zhang1],本[ben3]"
],
[
"日用品",
5,
"rì yòng pǐn",
"articles for daily use; CL:件[jian4],個|个[ge4]"
],
[
"日益",
6,
"rì yì",
"day by day; more and more; increasingly; more and more with each passing day"
],
[
"昔日",
6,
"xī rì",
"former days; in the past"
],
[
"与日俱增",
6,
"yǔ rì jù zēng",
"to increase steadily; to grow with each passing day"
],
[
"日新月异",
6,
"rì xīn yuè yì",
"daily renewal, monthly change (idiom); every day sees new developments; rapid progress"
]
],
"extraWords": [
[
"日本",
302.69,
"Rì běn",
"Japan"
],
[
"昨日",
181.34,
"zuó rì",
"yesterday"
],
[
"今日",
126.59,
"jīn rì",
"today"
],
[
"近日",
101.14,
"jìn rì",
"(in) the past few days; recently; (within) the next few days"
],
[
"生日快乐",
48.94,
"shēng rì kuài lè",
"Happy birthday"
],
[
"每日",
44.79,
"měi rì",
"daily; (soup etc) of the day"
],
[
"当日",
44.66,
"dāng rì",
"on that day"
],
[
"当日",
44.66,
"dàng rì",
"that very day; the same day"
],
[
"中日",
21.5,
"Zhōng Rì",
"China-Japan"
],
[
"早日",
18.62,
"zǎo rì",
"soon; shortly; on a day quite soon; promptly"
],
[
"交易日",
17.98,
"jiāo yì rì",
"working day (in banking, share trading)"
],
[
"末日",
16.9,
"Mò rì",
"Judgment Day (in Christian eschatology)"
],
[
"末日",
16.9,
"mò rì",
"last day; end; final days; doomsday"
],
[
"日本人",
16.56,
"Rì běn rén",
"Japanese person or people"
],
[
"周日",
15.19,
"Zhōu rì",
"Sunday; diurnal"
],
[
"日后",
13.66,
"rì hòu",
"sometime; someday (in the future)"
],
[
"日趋",
12.4,
"rì qū",
"(increasing) day by day; (more critical) with every passing day; gradually"
],
[
"明日",
11.7,
"míng rì",
"tomorrow"
],
[
"次日",
11.69,
"cì rì",
"next day; the morrow"
],
[
"即日",
11.33,
"jí rì",
"this or that very day; in the next few days"
],
[
"假日",
10.51,
"jià rì",
"holiday; non-working day"
],
[
"人民日报",
10.4,
"Rén mín Rì bào",
"People's Daily (PRC newspaper)"
],
[
"前日",
10.37,
"qián rì",
"day before yesterday"
],
[
"日落",
10.22,
"rì luò",
"sundown; sunset"
],
[
"日渐",
9.93,
"rì jiàn",
"to progress (or increase, change etc) day by day; more (or better etc) with each passing day"
],
[
"日元",
9.93,
"Rì yuán",
"Japanese yen (unit of currency); also written 日圓|日圆[Ri4 yuan2]"
],
[
"好日子",
9.36,
"hǎo rì zi",
"auspicious day; good day; happy life"
],
[
"纪念日",
9.06,
"jì niàn rì",
"day of commemoration; memorial day"
],
[
"平日",
8.74,
"píng rì",
"ordinary day; everyday; ordinarily; usually"
],
[
"日圆",
8.52,
"Rì yuán",
"Japanese yen (unit of currency); CL:個|个[ge4]"
],
[
"工作日",
8.3,
"gōng zuò rì",
"workday; working day; weekday"
],
[
"日产",
8.23,
"Rì chǎn",
"Nissan, Japanese car make; also transliterated 尼桑[Ni2 sang1]"
],
[
"日报",
8.1,
"rì bào",
"daily newspaper"
],
[
"抗日战争",
7.99,
"Kàng Rì Zhàn zhēng",
"(China's) War of Resistance against Japan (1937-1945)"
],
[
"节假日",
7.68,
"jié jià rì",
"public holiday"
],
[
"日日",
7.45,
"rì rì",
"every day"
],
[
"金正日",
7.0,
"Jīn Zhèng rì",
"Kim Jong-il (1942-2011), Dear Leader of North Korea 1982-2011"
],
[
"日内瓦",
6.57,
"Rì nèi wǎ",
"Geneva, Switzerland"
],
[
"日夜",
6.39,
"rì yè",
"day and night; around the clock"
],
[
"日志",
6.38,
"rì zhì",
"journal; log (computing)"
],
[
"日语",
6.36,
"Rì yǔ",
"Japanese language"
],
[
"尼日利亚",
6.29,
"Ní rì lì yà",
"Nigeria"
],
[
"往日",
6.14,
"wǎng rì",
"former days; the past"
],
[
"夏日",
6.11,
"xià rì",
"summertime"
],
[
"中国日报",
6.0,
"Zhōng guó Rì bào",
"China Daily (an English language newspaper)"
],
[
"日中",
5.78,
"Rì Zhōng",
"Japan-China"
],
[
"日中",
5.78,
"rì zhōng",
"noon; midday; zenith"
],
[
"世界末日",
5.48,
"shì jiè mò rì",
"end of the world"
],
[
"过日子",
5.46,
"guò rì zi",
"to live one's life; to pass one's days; to get along"
],
[
"星期日",
5.45,
"Xīng qī rì",
"Sunday; CL:個|个[ge4]"
],
[
"日出",
5.27,
"rì chū",
"sunrise"
]
],
"strokes": [
"M 349 664 Q 348 665 347 666 Q 322 687 292 696 Q 282 697 274 689 Q 270 682 279 670 Q 331 531 294 261 Q 287 216 271 169 Q 262 141 267 118 Q 277 81 291 65 Q 304 50 314 66 Q 324 79 332 102 L 339 137 Q 349 186 350 238 Q 350 316 351 391 L 352 420 Q 353 576 361 626 C 364 652 364 652 349 664 Z",
"M 608 120 Q 641 78 665 39 Q 675 18 688 19 Q 707 20 724 59 Q 745 104 740 157 Q 728 310 721 593 Q 720 629 738 654 Q 748 669 738 681 Q 716 703 656 730 Q 635 740 617 729 Q 512 684 349 664 C 319 660 332 620 361 626 Q 410 635 590 672 Q 624 679 640 666 Q 691 615 658 164 Q 657 163 657 159 Q 653 143 640 144 C 621 121 602 128 608 120 Z",
"M 351 391 Q 390 378 433 387 Q 493 399 554 411 Q 582 417 587 421 Q 596 428 591 437 Q 584 447 556 455 Q 531 461 450 435 Q 375 423 352 420 C 322 416 322 400 351 391 Z",
"M 332 102 Q 345 98 361 100 Q 440 115 608 120 C 638 121 661 122 640 144 Q 633 153 614 166 Q 596 178 561 170 Q 438 146 339 137 C 309 134 303 108 332 102 Z"
]
}